{
  "n_seeds": 16,
  "seeds": [
    20260613,
    20260614,
    20270101,
    19990412,
    20260720,
    271828,
    314159,
    40520000,
    42424242,
    13371337,
    90210,
    20261612,
    77777,
    20240229,
    20251231,
    555555
  ],
  "alpha": 0.1,
  "items": {
    "altmodel/arm1/A/naive/cqr_hiDstar": {
      "point": 0.7694610778443114,
      "point_kind": "across-seed mean (E)",
      "mean": 0.7694610778443114,
      "sd": 0.019648262997724087,
      "lo5": 0.7380239520958084,
      "hi95": 0.7919161676646707,
      "vmin": 0.7245508982035929,
      "vmax": 0.7964071856287425,
      "n_seeds": 16,
      "nn_derived": false,
      "seed0": 0.7724550898203593
    },
    "altmodel/arm1/A/naive/cqr_loDstar": {
      "point": 0.9025900900900902,
      "point_kind": "across-seed mean (E)",
      "mean": 0.9025900900900902,
      "sd": 0.02114844121620278,
      "lo5": 0.8746246246246246,
      "hi95": 0.933933933933934,
      "vmin": 0.8498498498498499,
      "vmax": 0.933933933933934,
      "n_seeds": 16,
      "nn_derived": false,
      "seed0": 0.8948948948948949
    },
    "altmodel/arm1/A/naive/cqr_marg/D": {
      "point": 0.8950625000000001,
      "point_kind": "across-seed mean (E)",
      "mean": 0.8950625000000001,
      "sd": 0.01045287041917196,
      "lo5": 0.88125,
      "hi95": 0.9085000000000001,
      "vmin": 0.879,
      "vmax": 0.919,
      "n_seeds": 16,
      "nn_derived": false,
      "seed0": 0.898
    },
    "altmodel/arm1/A/naive/cqr_marg/D*": {
      "point": 0.8890625,
      "point_kind": "across-seed mean (E)",
      "mean": 0.8890625,
      "sd": 0.009862175216452006,
      "lo5": 0.8745,
      "hi95": 0.9025000000000001,
      "vmin": 0.873,
      "vmax": 0.907,
      "n_seeds": 16,
      "nn_derived": false,
      "seed0": 0.888
    },
    "altmodel/arm1/A/naive/cqr_marg/f": {
      "point": 0.8731875,
      "point_kind": "across-seed mean (E)",
      "mean": 0.8731875,
      "sd": 0.01263971914244934,
      "lo5": 0.85175,
      "hi95": 0.88975,
      "vmin": 0.845,
      "vmax": 0.892,
      "n_seeds": 16,
      "nn_derived": false,
      "seed0": 0.872
    },
    "altmodel/arm1/A/naive/monitor_auc": {
      "point": 0.5009243125,
      "point_kind": "across-seed mean (E)",
      "mean": 0.5009243125,
      "sd": 0.01267401014132861,
      "lo5": 0.48074062500000003,
      "hi95": 0.5187405,
      "vmin": 0.47946900000000003,
      "vmax": 0.5206950000000001,
      "n_seeds": 16,
      "nn_derived": false,
      "seed0": 0.508731
    },
    "altmodel/arm1/A/naive/monitor_fires": {
      "point": 0.625,
      "point_kind": "across-seed mean (E)",
      "mean": 0.625,
      "sd": 0.5,
      "lo5": 0.0,
      "hi95": 1.0,
      "vmin": 0.0,
      "vmax": 1.0,
      "n_seeds": 16,
      "nn_derived": false,
      "seed0": 1.0
    },
    "altmodel/arm1/A/recal/cqr_hiDstar": {
      "point": 0.7954715568862275,
      "point_kind": "across-seed mean (E)",
      "mean": 0.7954715568862275,
      "sd": 0.03646830720678114,
      "lo5": 0.7477544910179641,
      "hi95": 0.8540419161676647,
      "vmin": 0.7275449101796407,
      "vmax": 0.8652694610778443,
      "n_seeds": 16,
      "nn_derived": false,
      "seed0": 0.8502994011976048
    },
    "altmodel/arm1/A/recal/cqr_loDstar": {
      "point": 0.9149774774774775,
      "point_kind": "across-seed mean (E)",
      "mean": 0.9149774774774775,
      "sd": 0.028334915422435297,
      "lo5": 0.8656156156156156,
      "hi95": 0.9451951951951952,
      "vmin": 0.8588588588588588,
      "vmax": 0.960960960960961,
      "n_seeds": 16,
      "nn_derived": false,
      "seed0": 0.8768768768768769
    },
    "altmodel/arm1/A/recal/cqr_marg/D": {
      "point": 0.90175,
      "point_kind": "across-seed mean (E)",
      "mean": 0.90175,
      "sd": 0.010214368964029717,
      "lo5": 0.88875,
      "hi95": 0.9185000000000001,
      "vmin": 0.888,
      "vmax": 0.92,
      "n_seeds": 16,
      "nn_derived": false,
      "seed0": 0.901
    },
    "altmodel/arm1/A/recal/cqr_marg/D*": {
      "point": 0.898375,
      "point_kind": "across-seed mean (E)",
      "mean": 0.898375,
      "sd": 0.013519738656251223,
      "lo5": 0.87975,
      "hi95": 0.9167500000000001,
      "vmin": 0.864,
      "vmax": 0.922,
      "n_seeds": 16,
      "nn_derived": false,
      "seed0": 0.904
    },
    "altmodel/arm1/A/recal/cqr_marg/f": {
      "point": 0.9034375,
      "point_kind": "across-seed mean (E)",
      "mean": 0.9034375,
      "sd": 0.013195801099844846,
      "lo5": 0.88975,
      "hi95": 0.92825,
      "vmin": 0.886,
      "vmax": 0.938,
      "n_seeds": 16,
      "nn_derived": false,
      "seed0": 0.91
    },
    "altmodel/arm1/B/naive/cqr_hiDstar": {
      "point": 0.9738023952095809,
      "point_kind": "across-seed mean (E)",
      "mean": 0.9738023952095809,
      "sd": 0.00721053567592353,
      "lo5": 0.9670658682634731,
      "hi95": 0.9865269461077845,
      "vmin": 0.9670658682634731,
      "vmax": 0.9910179640718563,
      "n_seeds": 16,
      "nn_derived": false,
      "seed0": 0.9850299401197605
    },
    "altmodel/arm1/B/naive/cqr_loDstar": {
      "point": 0.910472972972973,
      "point_kind": "across-seed mean (E)",
      "mean": 0.910472972972973,
      "sd": 0.019713938980855442,
      "lo5": 0.8836336336336336,
      "hi95": 0.9361861861861862,
      "vmin": 0.8678678678678678,
      "vmax": 0.9429429429429429,
      "n_seeds": 16,
      "nn_derived": false,
      "seed0": 0.8948948948948949
    },
    "altmodel/arm1/B/naive/cqr_marg/D": {
      "point": 0.8950625000000001,
      "point_kind": "across-seed mean (E)",
      "mean": 0.8950625000000001,
      "sd": 0.01045287041917196,
      "lo5": 0.88125,
      "hi95": 0.9085000000000001,
      "vmin": 0.879,
      "vmax": 0.919,
      "n_seeds": 16,
      "nn_derived": false,
      "seed0": 0.898
    },
    "altmodel/arm1/B/naive/cqr_marg/D*": {
      "point": 0.9565625,
      "point_kind": "across-seed mean (E)",
      "mean": 0.9565625,
      "sd": 0.00851640573638121,
      "lo5": 0.946,
      "hi95": 0.97125,
      "vmin": 0.943,
      "vmax": 0.975,
      "n_seeds": 16,
      "nn_derived": false,
      "seed0": 0.955
    },
    "altmodel/arm1/B/naive/cqr_marg/f": {
      "point": 0.8731875,
      "point_kind": "across-seed mean (E)",
      "mean": 0.8731875,
      "sd": 0.01263971914244934,
      "lo5": 0.85175,
      "hi95": 0.88975,
      "vmin": 0.845,
      "vmax": 0.892,
      "n_seeds": 16,
      "nn_derived": false,
      "seed0": 0.872
    },
    "altmodel/arm1/B/naive/monitor_auc": {
      "point": 0.5009243125,
      "point_kind": "across-seed mean (E)",
      "mean": 0.5009243125,
      "sd": 0.01267401014132861,
      "lo5": 0.48074062500000003,
      "hi95": 0.5187405,
      "vmin": 0.47946900000000003,
      "vmax": 0.5206950000000001,
      "n_seeds": 16,
      "nn_derived": false,
      "seed0": 0.508731
    },
    "altmodel/arm1/B/naive/monitor_fires": {
      "point": 0.625,
      "point_kind": "across-seed mean (E)",
      "mean": 0.625,
      "sd": 0.5,
      "lo5": 0.0,
      "hi95": 1.0,
      "vmin": 0.0,
      "vmax": 1.0,
      "n_seeds": 16,
      "nn_derived": false,
      "seed0": 1.0
    },
    "altmodel/arm1/B/recal/cqr_hiDstar": {
      "point": 0.7999625748502994,
      "point_kind": "across-seed mean (E)",
      "mean": 0.7999625748502994,
      "sd": 0.030202814622407193,
      "lo5": 0.7559880239520957,
      "hi95": 0.8450598802395209,
      "vmin": 0.7425149700598802,
      "vmax": 0.8562874251497006,
      "n_seeds": 16,
      "nn_derived": false,
      "seed0": 0.8293413173652695
    },
    "altmodel/arm1/B/recal/cqr_loDstar": {
      "point": 0.9089714714714714,
      "point_kind": "across-seed mean (E)",
      "mean": 0.9089714714714714,
      "sd": 0.027253389729651273,
      "lo5": 0.8663663663663663,
      "hi95": 0.93993993993994,
      "vmin": 0.8348348348348348,
      "vmax": 0.948948948948949,
      "n_seeds": 16,
      "nn_derived": false,
      "seed0": 0.8888888888888888
    },
    "altmodel/arm1/B/recal/cqr_marg/D": {
      "point": 0.90175,
      "point_kind": "across-seed mean (E)",
      "mean": 0.90175,
      "sd": 0.010214368964029717,
      "lo5": 0.88875,
      "hi95": 0.9185000000000001,
      "vmin": 0.888,
      "vmax": 0.92,
      "n_seeds": 16,
      "nn_derived": false,
      "seed0": 0.901
    },
    "altmodel/arm1/B/recal/cqr_marg/D*": {
      "point": 0.8978125000000001,
      "point_kind": "across-seed mean (E)",
      "mean": 0.8978125000000001,
      "sd": 0.012838581178100132,
      "lo5": 0.881,
      "hi95": 0.91125,
      "vmin": 0.86,
      "vmax": 0.921,
      "n_seeds": 16,
      "nn_derived": false,
      "seed0": 0.904
    },
    "altmodel/arm1/B/recal/cqr_marg/f": {
      "point": 0.9034375,
      "point_kind": "across-seed mean (E)",
      "mean": 0.9034375,
      "sd": 0.013195801099844846,
      "lo5": 0.88975,
      "hi95": 0.92825,
      "vmin": 0.886,
      "vmax": 0.938,
      "n_seeds": 16,
      "nn_derived": false,
      "seed0": 0.91
    },
    "altmodel/arm1/wall_biexpFit/abs_growth": {
      "point": 2.8408249274373807,
      "point_kind": "across-seed mean (E)",
      "mean": 2.8408249274373807,
      "sd": 0.3480952655485354,
      "lo5": 2.295840682515987,
      "hi95": 3.2714685246216164,
      "vmin": 2.131633622901448,
      "vmax": 3.434595399852972,
      "n_seeds": 16,
      "nn_derived": false,
      "seed0": 2.6090622721937904
    },
    "altmodel/arm1/wall_biexpFit/crlb_over_width/hi": {
      "point": 1.1307898085962549,
      "point_kind": "across-seed mean (E)",
      "mean": 1.1307898085962549,
      "sd": 0.12746689869609537,
      "lo5": 0.9898914347698995,
      "hi95": 1.3385500826327072,
      "vmin": 0.8966031161082009,
      "vmax": 1.4022029278960666,
      "n_seeds": 16,
      "nn_derived": false,
      "seed0": 1.0690004709170426
    },
    "altmodel/arm1/wall_biexpFit/crlb_over_width/lo": {
      "point": 0.38168516780513423,
      "point_kind": "across-seed mean (E)",
      "mean": 0.38168516780513423,
      "sd": 0.03129339486740235,
      "lo5": 0.34402714416185803,
      "hi95": 0.4216177821460968,
      "vmin": 0.3369846873347674,
      "vmax": 0.4733613384171474,
      "n_seeds": 16,
      "nn_derived": false,
      "seed0": 0.4043699300557466
    },
    "altmodel/arm1/wall_biexpFit/crlb_over_width/mid": {
      "point": 0.7159873926209352,
      "point_kind": "across-seed mean (E)",
      "mean": 0.7159873926209352,
      "sd": 0.06263707648441794,
      "lo5": 0.6418521409659074,
      "hi95": 0.8202378860425579,
      "vmin": 0.6175506635551353,
      "vmax": 0.8555396458800849,
      "n_seeds": 16,
      "nn_derived": false,
      "seed0": 0.6775441529617133
    },
    "altmodel/arm1/wall_dispJac/abs_growth": {
      "point": 2.7778519799187205,
      "point_kind": "across-seed mean (E)",
      "mean": 2.7778519799187205,
      "sd": 0.3487461118748602,
      "lo5": 2.254837691487836,
      "hi95": 3.2309977023102814,
      "vmin": 2.0424143492337112,
      "vmax": 3.365529294741949,
      "n_seeds": 16,
      "nn_derived": false,
      "seed0": 2.6152260049107747
    },
    "altmodel/arm1/wall_dispJac/crlb_over_width/hi": {
      "point": 1.319857941887003,
      "point_kind": "across-seed mean (E)",
      "mean": 1.319857941887003,
      "sd": 0.13623606206938382,
      "lo5": 1.1602217515609223,
      "hi95": 1.5269815983132708,
      "vmin": 1.0703155607647865,
      "vmax": 1.5667977564063869,
      "n_seeds": 16,
      "nn_derived": false,
      "seed0": 1.2582071336565
    },
    "altmodel/arm1/wall_dispJac/crlb_over_width/lo": {
      "point": 0.47039014478248453,
      "point_kind": "across-seed mean (E)",
      "mean": 0.47039014478248453,
      "sd": 0.03755139765736288,
      "lo5": 0.42690333572710054,
      "hi95": 0.5150339019573944,
      "vmin": 0.42340696608657313,
      "vmax": 0.5818059214006859,
      "n_seeds": 16,
      "nn_derived": false,
      "seed0": 0.49086953799606226
    },
    "altmodel/arm1/wall_dispJac/crlb_over_width/mid": {
      "point": 0.822201386802527,
      "point_kind": "across-seed mean (E)",
      "mean": 0.822201386802527,
      "sd": 0.07227497388776188,
      "lo5": 0.726542950334089,
      "hi95": 0.9475566553436618,
      "vmin": 0.7024718865249354,
      "vmax": 0.9574316453924828,
      "n_seeds": 16,
      "nn_derived": false,
      "seed0": 0.7481025429445161
    },
    "altmodel/arm1_lognormal/A/naive/cqr_marg/D": {
      "point": 0.8958125000000001,
      "point_kind": "across-seed mean (E)",
      "mean": 0.8958125000000001,
      "sd": 0.010120729552095878,
      "lo5": 0.88325,
      "hi95": 0.91025,
      "vmin": 0.878,
      "vmax": 0.917,
      "n_seeds": 16,
      "nn_derived": false,
      "seed0": 0.897
    },
    "altmodel/arm1_lognormal/A/naive/cqr_marg/D*": {
      "point": 0.8915625,
      "point_kind": "across-seed mean (E)",
      "mean": 0.8915625,
      "sd": 0.010210901037616621,
      "lo5": 0.877,
      "hi95": 0.90475,
      "vmin": 0.874,
      "vmax": 0.907,
      "n_seeds": 16,
      "nn_derived": false,
      "seed0": 0.889
    },
    "altmodel/arm1_lognormal/A/naive/cqr_marg/f": {
      "point": 0.8799375,
      "point_kind": "across-seed mean (E)",
      "mean": 0.8799375,
      "sd": 0.010822622910674975,
      "lo5": 0.86225,
      "hi95": 0.89425,
      "vmin": 0.854,
      "vmax": 0.898,
      "n_seeds": 16,
      "nn_derived": false,
      "seed0": 0.879
    },
    "altmodel/arm1_lognormal/A/naive/monitor_auc": {
      "point": 0.50119803125,
      "point_kind": "across-seed mean (E)",
      "mean": 0.50119803125,
      "sd": 0.012880587404396267,
      "lo5": 0.480660375,
      "hi95": 0.520160875,
      "vmin": 0.47898149999999995,
      "vmax": 0.520387,
      "n_seeds": 16,
      "nn_derived": false,
      "seed0": 0.508297
    },
    "altmodel/arm1_lognormal/A/recal/cqr_hiDstar": {
      "point": 0.7967814371257484,
      "point_kind": "across-seed mean (E)",
      "mean": 0.7967814371257484,
      "sd": 0.03929462499522961,
      "lo5": 0.7470059880239521,
      "hi95": 0.847305389221557,
      "vmin": 0.7425149700598802,
      "vmax": 0.8652694610778443,
      "n_seeds": 16,
      "nn_derived": false,
      "seed0": 0.8413173652694611
    },
    "altmodel/arm1_lognormal/A/recal/cqr_loDstar": {
      "point": 0.9168543543543544,
      "point_kind": "across-seed mean (E)",
      "mean": 0.9168543543543544,
      "sd": 0.027842631863493502,
      "lo5": 0.8753753753753754,
      "hi95": 0.9474474474474475,
      "vmin": 0.8348348348348348,
      "vmax": 0.9519519519519519,
      "n_seeds": 16,
      "nn_derived": false,
      "seed0": 0.9159159159159159
    },
    "altmodel/arm1_lognormal/A/recal/cqr_marg/D": {
      "point": 0.90225,
      "point_kind": "across-seed mean (E)",
      "mean": 0.90225,
      "sd": 0.01272530287786242,
      "lo5": 0.88675,
      "hi95": 0.9205000000000001,
      "vmin": 0.874,
      "vmax": 0.928,
      "n_seeds": 16,
      "nn_derived": false,
      "seed0": 0.895
    },
    "altmodel/arm1_lognormal/A/recal/cqr_marg/D*": {
      "point": 0.8992500000000001,
      "point_kind": "across-seed mean (E)",
      "mean": 0.8992500000000001,
      "sd": 0.017109451578976278,
      "lo5": 0.87775,
      "hi95": 0.92025,
      "vmin": 0.853,
      "vmax": 0.924,
      "n_seeds": 16,
      "nn_derived": false,
      "seed0": 0.913
    },
    "altmodel/arm1_lognormal/A/recal/cqr_marg/f": {
      "point": 0.9027499999999999,
      "point_kind": "across-seed mean (E)",
      "mean": 0.9027499999999999,
      "sd": 0.009560334722173705,
      "lo5": 0.89,
      "hi95": 0.917,
      "vmin": 0.884,
      "vmax": 0.923,
      "n_seeds": 16,
      "nn_derived": false,
      "seed0": 0.905
    },
    "altmodel/arm1_lognormal/A/recal/cqr_midDstar": {
      "point": 0.9844219219219219,
      "point_kind": "across-seed mean (E)",
      "mean": 0.9844219219219219,
      "sd": 0.0077706631653193916,
      "lo5": 0.9722222222222223,
      "hi95": 0.993993993993994,
      "vmin": 0.96996996996997,
      "vmax": 0.993993993993994,
      "n_seeds": 16,
      "nn_derived": false,
      "seed0": 0.9819819819819819
    },
    "altmodel/arm2/dispersion/dev0/auc": {
      "point": 0.5083188750000001,
      "point_kind": "across-seed mean (E)",
      "mean": 0.5083188750000001,
      "sd": 0.008315456556918571,
      "lo5": 0.494791125,
      "hi95": 0.519182875,
      "vmin": 0.4929495,
      "vmax": 0.5213215,
      "n_seeds": 16,
      "nn_derived": false,
      "seed0": 0.510893
    },
    "altmodel/arm2/dispersion/dev0/cov/D": {
      "point": 0.9005625,
      "point_kind": "across-seed mean (E)",
      "mean": 0.9005625,
      "sd": 0.009416076677682704,
      "lo5": 0.8895,
      "hi95": 0.91425,
      "vmin": 0.885,
      "vmax": 0.918,
      "n_seeds": 16,
      "nn_derived": false,
      "seed0": 0.913
    },
    "altmodel/arm2/dispersion/dev0/cov/D*": {
      "point": 0.9034375,
      "point_kind": "across-seed mean (E)",
      "mean": 0.9034375,
      "sd": 0.01303824502505355,
      "lo5": 0.88025,
      "hi95": 0.91825,
      "vmin": 0.869,
      "vmax": 0.919,
      "n_seeds": 16,
      "nn_derived": false,
      "seed0": 0.909
    },
    "altmodel/arm2/dispersion/dev0/cov/f": {
      "point": 0.8988750000000001,
      "point_kind": "across-seed mean (E)",
      "mean": 0.8988750000000001,
      "sd": 0.007446475676452593,
      "lo5": 0.88775,
      "hi95": 0.9097500000000001,
      "vmin": 0.887,
      "vmax": 0.912,
      "n_seeds": 16,
      "nn_derived": false,
      "seed0": 0.908
    },
    "altmodel/arm2/dispersion/dev0/fires": {
      "point": 0.875,
      "point_kind": "across-seed mean (E)",
      "mean": 0.875,
      "sd": 0.3415650255319866,
      "lo5": 0.0,
      "hi95": 1.0,
      "vmin": 0.0,
      "vmax": 1.0,
      "n_seeds": 16,
      "nn_derived": false,
      "seed0": 1.0
    },
    "altmodel/arm2/dispersion/dev1/auc": {
      "point": 0.50536703125,
      "point_kind": "across-seed mean (E)",
      "mean": 0.50536703125,
      "sd": 0.012893995406737132,
      "lo5": 0.489268375,
      "hi95": 0.52415775,
      "vmin": 0.487822,
      "vmax": 0.5248665,
      "n_seeds": 16,
      "nn_derived": false,
      "seed0": 0.5111455
    },
    "altmodel/arm2/dispersion/dev1/cov/D": {
      "point": 0.9007499999999999,
      "point_kind": "across-seed mean (E)",
      "mean": 0.9007499999999999,
      "sd": 0.008827985802737422,
      "lo5": 0.8885000000000001,
      "hi95": 0.913,
      "vmin": 0.887,
      "vmax": 0.913,
      "n_seeds": 16,
      "nn_derived": false,
      "seed0": 0.89
    },
    "altmodel/arm2/dispersion/dev1/cov/D*": {
      "point": 0.903875,
      "point_kind": "across-seed mean (E)",
      "mean": 0.903875,
      "sd": 0.010550671384640262,
      "lo5": 0.8875,
      "hi95": 0.9177500000000001,
      "vmin": 0.88,
      "vmax": 0.92,
      "n_seeds": 16,
      "nn_derived": false,
      "seed0": 0.92
    },
    "altmodel/arm2/dispersion/dev1/cov/f": {
      "point": 0.8981875000000001,
      "point_kind": "across-seed mean (E)",
      "mean": 0.8981875000000001,
      "sd": 0.010640919446488957,
      "lo5": 0.8855,
      "hi95": 0.9147500000000001,
      "vmin": 0.884,
      "vmax": 0.92,
      "n_seeds": 16,
      "nn_derived": false,
      "seed0": 0.887
    },
    "altmodel/arm2/dispersion/dev1/fires": {
      "point": 0.5625,
      "point_kind": "across-seed mean (E)",
      "mean": 0.5625,
      "sd": 0.51234753829798,
      "lo5": 0.0,
      "hi95": 1.0,
      "vmin": 0.0,
      "vmax": 1.0,
      "n_seeds": 16,
      "nn_derived": false,
      "seed0": 1.0
    },
    "altmodel/arm2/dispersion/dev2/auc": {
      "point": 0.5045769375,
      "point_kind": "across-seed mean (E)",
      "mean": 0.5045769375,
      "sd": 0.012174571369422679,
      "lo5": 0.488650375,
      "hi95": 0.523509875,
      "vmin": 0.48596950000000005,
      "vmax": 0.5315945,
      "n_seeds": 16,
      "nn_derived": false,
      "seed0": 0.501347
    },
    "altmodel/arm2/dispersion/dev2/cov/D": {
      "point": 0.8934375,
      "point_kind": "across-seed mean (E)",
      "mean": 0.8934375,
      "sd": 0.014174948559577457,
      "lo5": 0.87075,
      "hi95": 0.91125,
      "vmin": 0.861,
      "vmax": 0.912,
      "n_seeds": 16,
      "nn_derived": false,
      "seed0": 0.889
    },
    "altmodel/arm2/dispersion/dev2/cov/D*": {
      "point": 0.8905625,
      "point_kind": "across-seed mean (E)",
      "mean": 0.8905625,
      "sd": 0.010563892906184421,
      "lo5": 0.876,
      "hi95": 0.90725,
      "vmin": 0.876,
      "vmax": 0.908,
      "n_seeds": 16,
      "nn_derived": false,
      "seed0": 0.907
    },
    "altmodel/arm2/dispersion/dev2/cov/f": {
      "point": 0.881,
      "point_kind": "across-seed mean (E)",
      "mean": 0.881,
      "sd": 0.011899579824514825,
      "lo5": 0.866,
      "hi95": 0.899,
      "vmin": 0.863,
      "vmax": 0.905,
      "n_seeds": 16,
      "nn_derived": false,
      "seed0": 0.874
    },
    "altmodel/arm2/dispersion/dev2/fires": {
      "point": 0.6875,
      "point_kind": "across-seed mean (E)",
      "mean": 0.6875,
      "sd": 0.47871355387816905,
      "lo5": 0.0,
      "hi95": 1.0,
      "vmin": 0.0,
      "vmax": 1.0,
      "n_seeds": 16,
      "nn_derived": false,
      "seed0": 1.0
    },
    "altmodel/arm2/dispersion/dev3/auc": {
      "point": 0.5016778749999999,
      "point_kind": "across-seed mean (E)",
      "mean": 0.5016778749999999,
      "sd": 0.01280608184874151,
      "lo5": 0.485681625,
      "hi95": 0.5194221250000001,
      "vmin": 0.4852995,
      "vmax": 0.5250130000000001,
      "n_seeds": 16,
      "nn_derived": false,
      "seed0": 0.5072794999999999
    },
    "altmodel/arm2/dispersion/dev3/cov/D": {
      "point": 0.8955,
      "point_kind": "across-seed mean (E)",
      "mean": 0.8955,
      "sd": 0.0093166517590817,
      "lo5": 0.88025,
      "hi95": 0.908,
      "vmin": 0.878,
      "vmax": 0.908,
      "n_seeds": 16,
      "nn_derived": false,
      "seed0": 0.896
    },
    "altmodel/arm2/dispersion/dev3/cov/D*": {
      "point": 0.88775,
      "point_kind": "across-seed mean (E)",
      "mean": 0.88775,
      "sd": 0.011699002806507352,
      "lo5": 0.87,
      "hi95": 0.908,
      "vmin": 0.87,
      "vmax": 0.908,
      "n_seeds": 16,
      "nn_derived": false,
      "seed0": 0.908
    },
    "altmodel/arm2/dispersion/dev3/cov/f": {
      "point": 0.854875,
      "point_kind": "across-seed mean (E)",
      "mean": 0.854875,
      "sd": 0.01120639698267617,
      "lo5": 0.8392499999999999,
      "hi95": 0.87,
      "vmin": 0.837,
      "vmax": 0.882,
      "n_seeds": 16,
      "nn_derived": false,
      "seed0": 0.855
    },
    "altmodel/arm2/dispersion/dev3/fires": {
      "point": 0.5,
      "point_kind": "across-seed mean (E)",
      "mean": 0.5,
      "sd": 0.5163977794943222,
      "lo5": 0.0,
      "hi95": 1.0,
      "vmin": 0.0,
      "vmax": 1.0,
      "n_seeds": 16,
      "nn_derived": false,
      "seed0": 1.0
    },
    "altmodel/arm2/dispersion/dev4/auc": {
      "point": 0.5045650625,
      "point_kind": "across-seed mean (E)",
      "mean": 0.5045650625,
      "sd": 0.010375301039608424,
      "lo5": 0.4902965,
      "hi95": 0.5202567499999999,
      "vmin": 0.488084,
      "vmax": 0.5205845,
      "n_seeds": 16,
      "nn_derived": false,
      "seed0": 0.49223500000000003
    },
    "altmodel/arm2/dispersion/dev4/cov/D": {
      "point": 0.8900625,
      "point_kind": "across-seed mean (E)",
      "mean": 0.8900625,
      "sd": 0.01604356049427102,
      "lo5": 0.8714999999999999,
      "hi95": 0.9077500000000001,
      "vmin": 0.84,
      "vmax": 0.913,
      "n_seeds": 16,
      "nn_derived": false,
      "seed0": 0.885
    },
    "altmodel/arm2/dispersion/dev4/cov/D*": {
      "point": 0.8759375,
      "point_kind": "across-seed mean (E)",
      "mean": 0.8759375,
      "sd": 0.014585237970861739,
      "lo5": 0.85775,
      "hi95": 0.8965000000000001,
      "vmin": 0.851,
      "vmax": 0.901,
      "n_seeds": 16,
      "nn_derived": false,
      "seed0": 0.893
    },
    "altmodel/arm2/dispersion/dev4/cov/f": {
      "point": 0.790625,
      "point_kind": "across-seed mean (E)",
      "mean": 0.790625,
      "sd": 0.015999479158189278,
      "lo5": 0.76725,
      "hi95": 0.81475,
      "vmin": 0.753,
      "vmax": 0.817,
      "n_seeds": 16,
      "nn_derived": false,
      "seed0": 0.782
    },
    "altmodel/arm2/dispersion/dev4/fires": {
      "point": 0.5,
      "point_kind": "across-seed mean (E)",
      "mean": 0.5,
      "sd": 0.5163977794943222,
      "lo5": 0.0,
      "hi95": 1.0,
      "vmin": 0.0,
      "vmax": 1.0,
      "n_seeds": 16,
      "nn_derived": false,
      "seed0": 0.0
    },
    "altmodel/arm2/stretched/dev0/auc": {
      "point": 0.5082573125000001,
      "point_kind": "across-seed mean (E)",
      "mean": 0.5082573125000001,
      "sd": 0.009506913487694117,
      "lo5": 0.49686337499999994,
      "hi95": 0.522834125,
      "vmin": 0.4890285,
      "vmax": 0.530186,
      "n_seeds": 16,
      "nn_derived": false,
      "seed0": 0.4996205
    },
    "altmodel/arm2/stretched/dev0/cov/D": {
      "point": 0.901875,
      "point_kind": "across-seed mean (E)",
      "mean": 0.901875,
      "sd": 0.01328093872184243,
      "lo5": 0.8835,
      "hi95": 0.91925,
      "vmin": 0.873,
      "vmax": 0.923,
      "n_seeds": 16,
      "nn_derived": false,
      "seed0": 0.899
    },
    "altmodel/arm2/stretched/dev0/cov/D*": {
      "point": 0.8966875000000001,
      "point_kind": "across-seed mean (E)",
      "mean": 0.8966875000000001,
      "sd": 0.01222957480863502,
      "lo5": 0.88025,
      "hi95": 0.91525,
      "vmin": 0.869,
      "vmax": 0.919,
      "n_seeds": 16,
      "nn_derived": false,
      "seed0": 0.914
    },
    "altmodel/arm2/stretched/dev0/cov/f": {
      "point": 0.9015,
      "point_kind": "across-seed mean (E)",
      "mean": 0.9015,
      "sd": 0.009702233419854087,
      "lo5": 0.89075,
      "hi95": 0.91825,
      "vmin": 0.884,
      "vmax": 0.922,
      "n_seeds": 16,
      "nn_derived": false,
      "seed0": 0.9
    },
    "altmodel/arm2/stretched/dev0/fires": {
      "point": 0.9375,
      "point_kind": "across-seed mean (E)",
      "mean": 0.9375,
      "sd": 0.25,
      "lo5": 0.75,
      "hi95": 1.0,
      "vmin": 0.0,
      "vmax": 1.0,
      "n_seeds": 16,
      "nn_derived": false,
      "seed0": 1.0
    },
    "altmodel/arm2/stretched/dev1/auc": {
      "point": 0.50448996875,
      "point_kind": "across-seed mean (E)",
      "mean": 0.50448996875,
      "sd": 0.0119940365396986,
      "lo5": 0.494919875,
      "hi95": 0.53122575,
      "vmin": 0.4939175,
      "vmax": 0.5327655,
      "n_seeds": 16,
      "nn_derived": false,
      "seed0": 0.496787
    },
    "altmodel/arm2/stretched/dev1/cov/D": {
      "point": 0.8965000000000001,
      "point_kind": "across-seed mean (E)",
      "mean": 0.8965000000000001,
      "sd": 0.012743625857659204,
      "lo5": 0.87575,
      "hi95": 0.91125,
      "vmin": 0.872,
      "vmax": 0.915,
      "n_seeds": 16,
      "nn_derived": false,
      "seed0": 0.91
    },
    "altmodel/arm2/stretched/dev1/cov/D*": {
      "point": 0.867375,
      "point_kind": "across-seed mean (E)",
      "mean": 0.867375,
      "sd": 0.010688779163215985,
      "lo5": 0.85525,
      "hi95": 0.88575,
      "vmin": 0.85,
      "vmax": 0.888,
      "n_seeds": 16,
      "nn_derived": false,
      "seed0": 0.888
    },
    "altmodel/arm2/stretched/dev1/cov/f": {
      "point": 0.8868125,
      "point_kind": "across-seed mean (E)",
      "mean": 0.8868125,
      "sd": 0.011196539644015029,
      "lo5": 0.869,
      "hi95": 0.9015,
      "vmin": 0.869,
      "vmax": 0.909,
      "n_seeds": 16,
      "nn_derived": false,
      "seed0": 0.884
    },
    "altmodel/arm2/stretched/dev1/fires": {
      "point": 0.5625,
      "point_kind": "across-seed mean (E)",
      "mean": 0.5625,
      "sd": 0.51234753829798,
      "lo5": 0.0,
      "hi95": 1.0,
      "vmin": 0.0,
      "vmax": 1.0,
      "n_seeds": 16,
      "nn_derived": false,
      "seed0": 0.0
    },
    "altmodel/arm2/stretched/dev2/auc": {
      "point": 0.5071574062499999,
      "point_kind": "across-seed mean (E)",
      "mean": 0.5071574062499999,
      "sd": 0.010115530264925557,
      "lo5": 0.49445,
      "hi95": 0.52044475,
      "vmin": 0.49175899999999995,
      "vmax": 0.5362165,
      "n_seeds": 16,
      "nn_derived": false,
      "seed0": 0.507449
    },
    "altmodel/arm2/stretched/dev2/cov/D": {
      "point": 0.9036875000000001,
      "point_kind": "across-seed mean (E)",
      "mean": 0.9036875000000001,
      "sd": 0.009890862786767736,
      "lo5": 0.88975,
      "hi95": 0.91825,
      "vmin": 0.889,
      "vmax": 0.922,
      "n_seeds": 16,
      "nn_derived": false,
      "seed0": 0.9
    },
    "altmodel/arm2/stretched/dev2/cov/D*": {
      "point": 0.8290625,
      "point_kind": "across-seed mean (E)",
      "mean": 0.8290625,
      "sd": 0.015233597736582088,
      "lo5": 0.8087500000000001,
      "hi95": 0.8454999999999999,
      "vmin": 0.808,
      "vmax": 0.847,
      "n_seeds": 16,
      "nn_derived": false,
      "seed0": 0.834
    },
    "altmodel/arm2/stretched/dev2/cov/f": {
      "point": 0.8679999999999999,
      "point_kind": "across-seed mean (E)",
      "mean": 0.8679999999999999,
      "sd": 0.017727567985109157,
      "lo5": 0.83475,
      "hi95": 0.886,
      "vmin": 0.834,
      "vmax": 0.886,
      "n_seeds": 16,
      "nn_derived": false,
      "seed0": 0.853
    },
    "altmodel/arm2/stretched/dev2/fires": {
      "point": 0.5625,
      "point_kind": "across-seed mean (E)",
      "mean": 0.5625,
      "sd": 0.51234753829798,
      "lo5": 0.0,
      "hi95": 1.0,
      "vmin": 0.0,
      "vmax": 1.0,
      "n_seeds": 16,
      "nn_derived": false,
      "seed0": 1.0
    },
    "altmodel/arm2/stretched/dev3/auc": {
      "point": 0.5155523750000001,
      "point_kind": "across-seed mean (E)",
      "mean": 0.5155523750000001,
      "sd": 0.011431838858352276,
      "lo5": 0.49996487500000003,
      "hi95": 0.53449575,
      "vmin": 0.496015,
      "vmax": 0.538383,
      "n_seeds": 16,
      "nn_derived": false,
      "seed0": 0.5169865
    },
    "altmodel/arm2/stretched/dev3/cov/D": {
      "point": 0.898625,
      "point_kind": "across-seed mean (E)",
      "mean": 0.898625,
      "sd": 0.00890599049329533,
      "lo5": 0.88725,
      "hi95": 0.913,
      "vmin": 0.882,
      "vmax": 0.916,
      "n_seeds": 16,
      "nn_derived": false,
      "seed0": 0.916
    },
    "altmodel/arm2/stretched/dev3/cov/D*": {
      "point": 0.7920625,
      "point_kind": "across-seed mean (E)",
      "mean": 0.7920625,
      "sd": 0.007619875327064092,
      "lo5": 0.781,
      "hi95": 0.80425,
      "vmin": 0.781,
      "vmax": 0.805,
      "n_seeds": 16,
      "nn_derived": false,
      "seed0": 0.799
    },
    "altmodel/arm2/stretched/dev3/cov/f": {
      "point": 0.82475,
      "point_kind": "across-seed mean (E)",
      "mean": 0.82475,
      "sd": 0.01674713905915473,
      "lo5": 0.797,
      "hi95": 0.84825,
      "vmin": 0.797,
      "vmax": 0.849,
      "n_seeds": 16,
      "nn_derived": false,
      "seed0": 0.84
    },
    "altmodel/arm2/stretched/dev3/fires": {
      "point": 0.75,
      "point_kind": "across-seed mean (E)",
      "mean": 0.75,
      "sd": 0.4472135954999579,
      "lo5": 0.0,
      "hi95": 1.0,
      "vmin": 0.0,
      "vmax": 1.0,
      "n_seeds": 16,
      "nn_derived": false,
      "seed0": 1.0
    },
    "altmodel/arm2/stretched/dev4/auc": {
      "point": 0.53089690625,
      "point_kind": "across-seed mean (E)",
      "mean": 0.53089690625,
      "sd": 0.012977915557102829,
      "lo5": 0.51437625,
      "hi95": 0.5513865,
      "vmin": 0.502176,
      "vmax": 0.5550225,
      "n_seeds": 16,
      "nn_derived": false,
      "seed0": 0.5291379999999999
    },
    "altmodel/arm2/stretched/dev4/cov/D": {
      "point": 0.8943125000000001,
      "point_kind": "across-seed mean (E)",
      "mean": 0.8943125000000001,
      "sd": 0.011510683443363976,
      "lo5": 0.878,
      "hi95": 0.9145000000000001,
      "vmin": 0.875,
      "vmax": 0.919,
      "n_seeds": 16,
      "nn_derived": false,
      "seed0": 0.897
    },
    "altmodel/arm2/stretched/dev4/cov/D*": {
      "point": 0.769875,
      "point_kind": "across-seed mean (E)",
      "mean": 0.769875,
      "sd": 0.01581929201955639,
      "lo5": 0.74875,
      "hi95": 0.79325,
      "vmin": 0.736,
      "vmax": 0.797,
      "n_seeds": 16,
      "nn_derived": false,
      "seed0": 0.792
    },
    "altmodel/arm2/stretched/dev4/cov/f": {
      "point": 0.756375,
      "point_kind": "across-seed mean (E)",
      "mean": 0.756375,
      "sd": 0.013144707426692069,
      "lo5": 0.741,
      "hi95": 0.7827500000000001,
      "vmin": 0.738,
      "vmax": 0.785,
      "n_seeds": 16,
      "nn_derived": false,
      "seed0": 0.754
    },
    "altmodel/arm2/stretched/dev4/fires": {
      "point": 1.0,
      "point_kind": "across-seed mean (E)",
      "mean": 1.0,
      "sd": 0.0,
      "lo5": 1.0,
      "hi95": 1.0,
      "vmin": 1.0,
      "vmax": 1.0,
      "n_seeds": 16,
      "nn_derived": false,
      "seed0": 1.0
    },
    "altmodel/arm2/triexp/dev0/auc": {
      "point": 0.5035278125,
      "point_kind": "across-seed mean (E)",
      "mean": 0.5035278125,
      "sd": 0.012585124349637286,
      "lo5": 0.4856475,
      "hi95": 0.522985625,
      "vmin": 0.48439800000000005,
      "vmax": 0.5304815,
      "n_seeds": 16,
      "nn_derived": false,
      "seed0": 0.4895965
    },
    "altmodel/arm2/triexp/dev0/cov/D": {
      "point": 0.901125,
      "point_kind": "across-seed mean (E)",
      "mean": 0.901125,
      "sd": 0.01357387196049824,
      "lo5": 0.87775,
      "hi95": 0.92,
      "vmin": 0.877,
      "vmax": 0.929,
      "n_seeds": 16,
      "nn_derived": false,
      "seed0": 0.898
    },
    "altmodel/arm2/triexp/dev0/cov/D*": {
      "point": 0.9045000000000001,
      "point_kind": "across-seed mean (E)",
      "mean": 0.9045000000000001,
      "sd": 0.011552777443829987,
      "lo5": 0.8835,
      "hi95": 0.92025,
      "vmin": 0.879,
      "vmax": 0.924,
      "n_seeds": 16,
      "nn_derived": false,
      "seed0": 0.924
    },
    "altmodel/arm2/triexp/dev0/cov/f": {
      "point": 0.902375,
      "point_kind": "across-seed mean (E)",
      "mean": 0.902375,
      "sd": 0.009105858919765165,
      "lo5": 0.89,
      "hi95": 0.9157500000000001,
      "vmin": 0.887,
      "vmax": 0.918,
      "n_seeds": 16,
      "nn_derived": false,
      "seed0": 0.893
    },
    "altmodel/arm2/triexp/dev0/fires": {
      "point": 0.6875,
      "point_kind": "across-seed mean (E)",
      "mean": 0.6875,
      "sd": 0.47871355387816905,
      "lo5": 0.0,
      "hi95": 1.0,
      "vmin": 0.0,
      "vmax": 1.0,
      "n_seeds": 16,
      "nn_derived": false,
      "seed0": 0.0
    },
    "altmodel/arm2/triexp/dev1/auc": {
      "point": 0.5073076562500001,
      "point_kind": "across-seed mean (E)",
      "mean": 0.5073076562500001,
      "sd": 0.009755719035039134,
      "lo5": 0.4961075,
      "hi95": 0.524344125,
      "vmin": 0.4944905,
      "vmax": 0.5281335,
      "n_seeds": 16,
      "nn_derived": false,
      "seed0": 0.4966465
    },
    "altmodel/arm2/triexp/dev1/cov/D": {
      "point": 0.903125,
      "point_kind": "across-seed mean (E)",
      "mean": 0.903125,
      "sd": 0.012214062933083882,
      "lo5": 0.88425,
      "hi95": 0.91725,
      "vmin": 0.87,
      "vmax": 0.921,
      "n_seeds": 16,
      "nn_derived": false,
      "seed0": 0.912
    },
    "altmodel/arm2/triexp/dev1/cov/D*": {
      "point": 0.8740625,
      "point_kind": "across-seed mean (E)",
      "mean": 0.8740625,
      "sd": 0.011084335794263914,
      "lo5": 0.85775,
      "hi95": 0.89025,
      "vmin": 0.851,
      "vmax": 0.894,
      "n_seeds": 16,
      "nn_derived": false,
      "seed0": 0.872
    },
    "altmodel/arm2/triexp/dev1/cov/f": {
      "point": 0.9005624999999999,
      "point_kind": "across-seed mean (E)",
      "mean": 0.9005624999999999,
      "sd": 0.00939481239833985,
      "lo5": 0.89,
      "hi95": 0.9155,
      "vmin": 0.887,
      "vmax": 0.926,
      "n_seeds": 16,
      "nn_derived": false,
      "seed0": 0.9
    },
    "altmodel/arm2/triexp/dev1/fires": {
      "point": 0.6875,
      "point_kind": "across-seed mean (E)",
      "mean": 0.6875,
      "sd": 0.47871355387816905,
      "lo5": 0.0,
      "hi95": 1.0,
      "vmin": 0.0,
      "vmax": 1.0,
      "n_seeds": 16,
      "nn_derived": false,
      "seed0": 0.0
    },
    "altmodel/arm2/triexp/dev2/auc": {
      "point": 0.5110175625,
      "point_kind": "across-seed mean (E)",
      "mean": 0.5110175625,
      "sd": 0.012333890513371403,
      "lo5": 0.49242625000000007,
      "hi95": 0.529561125,
      "vmin": 0.48934600000000006,
      "vmax": 0.540498,
      "n_seeds": 16,
      "nn_derived": false,
      "seed0": 0.509151
    },
    "altmodel/arm2/triexp/dev2/cov/D": {
      "point": 0.900375,
      "point_kind": "across-seed mean (E)",
      "mean": 0.900375,
      "sd": 0.01398511113053213,
      "lo5": 0.87975,
      "hi95": 0.91925,
      "vmin": 0.873,
      "vmax": 0.92,
      "n_seeds": 16,
      "nn_derived": false,
      "seed0": 0.885
    },
    "altmodel/arm2/triexp/dev2/cov/D*": {
      "point": 0.8334374999999999,
      "point_kind": "across-seed mean (E)",
      "mean": 0.8334374999999999,
      "sd": 0.009939609314924481,
      "lo5": 0.821,
      "hi95": 0.8485,
      "vmin": 0.818,
      "vmax": 0.859,
      "n_seeds": 16,
      "nn_derived": false,
      "seed0": 0.836
    },
    "altmodel/arm2/triexp/dev2/cov/f": {
      "point": 0.90175,
      "point_kind": "across-seed mean (E)",
      "mean": 0.90175,
      "sd": 0.009504384952922178,
      "lo5": 0.886,
      "hi95": 0.91325,
      "vmin": 0.886,
      "vmax": 0.914,
      "n_seeds": 16,
      "nn_derived": false,
      "seed0": 0.903
    },
    "altmodel/arm2/triexp/dev2/fires": {
      "point": 0.875,
      "point_kind": "across-seed mean (E)",
      "mean": 0.875,
      "sd": 0.3415650255319866,
      "lo5": 0.0,
      "hi95": 1.0,
      "vmin": 0.0,
      "vmax": 1.0,
      "n_seeds": 16,
      "nn_derived": false,
      "seed0": 1.0
    },
    "altmodel/arm2/triexp/dev3/auc": {
      "point": 0.51598215625,
      "point_kind": "across-seed mean (E)",
      "mean": 0.51598215625,
      "sd": 0.0108862170085522,
      "lo5": 0.503433875,
      "hi95": 0.5328528749999999,
      "vmin": 0.5010365,
      "vmax": 0.5462549999999999,
      "n_seeds": 16,
      "nn_derived": false,
      "seed0": 0.5117345
    },
    "altmodel/arm2/triexp/dev3/cov/D": {
      "point": 0.9097500000000001,
      "point_kind": "across-seed mean (E)",
      "mean": 0.9097500000000001,
      "sd": 0.011468798251487972,
      "lo5": 0.8945000000000001,
      "hi95": 0.929,
      "vmin": 0.89,
      "vmax": 0.932,
      "n_seeds": 16,
      "nn_derived": false,
      "seed0": 0.92
    },
    "altmodel/arm2/triexp/dev3/cov/D*": {
      "point": 0.7951875,
      "point_kind": "across-seed mean (E)",
      "mean": 0.7951875,
      "sd": 0.01376090476676587,
      "lo5": 0.7765,
      "hi95": 0.8154999999999999,
      "vmin": 0.769,
      "vmax": 0.823,
      "n_seeds": 16,
      "nn_derived": false,
      "seed0": 0.823
    },
    "altmodel/arm2/triexp/dev3/cov/f": {
      "point": 0.90225,
      "point_kind": "across-seed mean (E)",
      "mean": 0.90225,
      "sd": 0.012871156384205225,
      "lo5": 0.883,
      "hi95": 0.9187500000000001,
      "vmin": 0.883,
      "vmax": 0.921,
      "n_seeds": 16,
      "nn_derived": false,
      "seed0": 0.908
    },
    "altmodel/arm2/triexp/dev3/fires": {
      "point": 1.0,
      "point_kind": "across-seed mean (E)",
      "mean": 1.0,
      "sd": 0.0,
      "lo5": 1.0,
      "hi95": 1.0,
      "vmin": 1.0,
      "vmax": 1.0,
      "n_seeds": 16,
      "nn_derived": false,
      "seed0": 1.0
    },
    "altmodel/arm2/triexp/dev4/auc": {
      "point": 0.53150009375,
      "point_kind": "across-seed mean (E)",
      "mean": 0.53150009375,
      "sd": 0.012240355093186286,
      "lo5": 0.5151231249999999,
      "hi95": 0.54808875,
      "vmin": 0.504445,
      "vmax": 0.5513669999999999,
      "n_seeds": 16,
      "nn_derived": false,
      "seed0": 0.5401455
    },
    "altmodel/arm2/triexp/dev4/cov/D": {
      "point": 0.9105,
      "point_kind": "across-seed mean (E)",
      "mean": 0.9105,
      "sd": 0.006703233050799697,
      "lo5": 0.8995,
      "hi95": 0.91825,
      "vmin": 0.895,
      "vmax": 0.919,
      "n_seeds": 16,
      "nn_derived": false,
      "seed0": 0.895
    },
    "altmodel/arm2/triexp/dev4/cov/D*": {
      "point": 0.7688125,
      "point_kind": "across-seed mean (E)",
      "mean": 0.7688125,
      "sd": 0.018045197883832343,
      "lo5": 0.7364999999999999,
      "hi95": 0.7877500000000001,
      "vmin": 0.72,
      "vmax": 0.79,
      "n_seeds": 16,
      "nn_derived": false,
      "seed0": 0.762
    },
    "altmodel/arm2/triexp/dev4/cov/f": {
      "point": 0.9038125,
      "point_kind": "across-seed mean (E)",
      "mean": 0.9038125,
      "sd": 0.012117308557046277,
      "lo5": 0.8875,
      "hi95": 0.922,
      "vmin": 0.88,
      "vmax": 0.925,
      "n_seeds": 16,
      "nn_derived": false,
      "seed0": 0.897
    },
    "altmodel/arm2/triexp/dev4/fires": {
      "point": 1.0,
      "point_kind": "across-seed mean (E)",
      "mean": 1.0,
      "sd": 0.0,
      "lo5": 1.0,
      "hi95": 1.0,
      "vmin": 1.0,
      "vmax": 1.0,
      "n_seeds": 16,
      "nn_derived": false,
      "seed0": 1.0
    },
    "altmodel/continuity/cv0_recal_hiDstar_A": {
      "point": 0.7982784431137724,
      "point_kind": "across-seed mean (E)",
      "mean": 0.7982784431137724,
      "sd": 0.03629017532051239,
      "lo5": 0.75,
      "hi95": 0.8420658682634731,
      "vmin": 0.7275449101796407,
      "vmax": 0.844311377245509,
      "n_seeds": 16,
      "nn_derived": false,
      "seed0": 0.8383233532934131
    },
    "altmodel/continuity/gen_max_abs_err": {
      "point": 0.0,
      "point_kind": "across-seed mean (E)",
      "mean": 0.0,
      "sd": 0.0,
      "lo5": 0.0,
      "hi95": 0.0,
      "vmin": 0.0,
      "vmax": 0.0,
      "n_seeds": 16,
      "nn_derived": false,
      "seed0": 0.0
    }
  }
}